escolour/__init__.py
escolour/colours.py
escolour-1.1.dist-info/LICENCE
escolour-1.1.dist-info/METADATA
escolour-1.1.dist-info/WHEEL
escolour-1.1.dist-info/top_level.txt
escolour-1.1.dist-info/RECORD
