Metadata-Version: 2.1
Name: escolour
Version: 1.1
Summary: A basic package for having vars for all term colours. Useful for use in formatted strings i.e: f"{RED}This is red{RST}"
Home-page: https://github.com/lewisyouldon/escolour
Author: Lewis Youldon
Author-email: lewisyouldon@gmail.com
License: MIT Licence
Platform: UNKNOWN
Classifier: Programming Language :: Python :: 3
Classifier: License :: OSI Approved :: MIT License
Classifier: Operating System :: OS Independent
Requires-Python: >=3.6
